REMclust/GaussianMixture.py
REMclust/REM.py
REMclust/__init__.py
REMclust/overlap.py
REMclust-1.2.dist-info/LICENSE.txt
REMclust-1.2.dist-info/METADATA
REMclust-1.2.dist-info/WHEEL
REMclust-1.2.dist-info/top_level.txt
REMclust-1.2.dist-info/RECORD
