Metadata-Version: 2.1
Name: REMclust
Version: 1.2
Summary: This is the official implementation of Reinforced EM, a parametric density-based clustering method
Home-page: https://github.com/r-swords/REMclust
Download-URL: https://github.com/r-swords/REMclust/archive/refs/tags/v_1.tar.gz
Author: Joshua Tobin, Ralph Swords, Mimi Zhang
Author-email: tobinjo@tcd.ie
License: MIT
Keywords: REM,Reinforced EM,Clustering,Density-Based Clustering,Parametric Density-Based Clustering,Gaussian Mixture Models
Classifier: License :: OSI Approved :: MIT License
Classifier: Programming Language :: Python :: 3
License-File: LICENSE.txt
Requires-Dist: numpy
Requires-Dist: matplotlib
Requires-Dist: scipy
Requires-Dist: scikit-learn
Requires-Dist: pandas
Requires-Dist: seaborn
Requires-Dist: statsmodels
Requires-Dist: mpmath
